ml_nlp_tk/__init__.py
ml_nlp_tk/file.py
ml_nlp_tk/rand.py
ml_nlp_tk/text.py
ml_nlp_tk/vectorize.py
ml_nlp_tk-1.1.0.dist-info/METADATA
ml_nlp_tk-1.1.0.dist-info/WHEEL
ml_nlp_tk-1.1.0.dist-info/top_level.txt
ml_nlp_tk-1.1.0.dist-info/RECORD
